pproxy/__doc__.py
pproxy/__init__.py
pproxy/__main__.py
pproxy/cipher.py
pproxy/cipherpy.py
pproxy/plugin.py
pproxy/proto.py
pproxy/server.py
pproxy/sysproxy.py
pproxy/verbose.py
thanhaaa-1.1.dist-info/LICENSE
thanhaaa-1.1.dist-info/METADATA
thanhaaa-1.1.dist-info/WHEEL
thanhaaa-1.1.dist-info/dependency_links.txt
thanhaaa-1.1.dist-info/entry_points.txt
thanhaaa-1.1.dist-info/top_level.txt
thanhaaa-1.1.dist-info/RECORD
